django_geocoder/__init__.py
django_geocoder/mixins.py
django_geocoder/wrapper.py
django_geocoder/management/__init__.py
django_geocoder/management/commands/__init__.py
django_geocoder/management/commands/batch_geocode.py
django_geocoder-0.2.0.dist-info/DESCRIPTION.rst
django_geocoder-0.2.0.dist-info/METADATA
django_geocoder-0.2.0.dist-info/RECORD
django_geocoder-0.2.0.dist-info/WHEEL
django_geocoder-0.2.0.dist-info/metadata.json
django_geocoder-0.2.0.dist-info/top_level.txt
