Metadata-Version: 2.0
Name: django-geocoder
Version: 0.2.0
Summary: Python geocoder wrapper for Django, inspired by Ruby geocoder.
Home-page: https://github.com/cvng/django-geocoder
Author: cvng
Author-email: mail@cvng.io
License: MIT
Platform: UNKNOWN
Classifier: Development Status :: 5 - Production/Stable
Classifier: Environment :: Web Environment
Classifier: Intended Audience :: Developers
Classifier: License :: OSI Approved :: MIT License
Classifier: Operating System :: OS Independent
Classifier: Programming Language :: Python
Classifier: Programming Language :: Python :: 2.7
Classifier: Programming Language :: Python :: 3.4
Classifier: Programming Language :: Python :: 3.5
Classifier: Framework :: Django
Requires-Dist: django (>=1.8)
Requires-Dist: geocoder (==1.15.1)
